README.rst
setup.py
openlegis/__init__.py
openlegis.recipe.sagl.egg-info/PKG-INFO
openlegis.recipe.sagl.egg-info/PKG-INFO~
openlegis.recipe.sagl.egg-info/SOURCES.txt
openlegis.recipe.sagl.egg-info/dependency_links.txt
openlegis.recipe.sagl.egg-info/entry_points.txt
openlegis.recipe.sagl.egg-info/namespace_packages.txt
openlegis.recipe.sagl.egg-info/not-zip-safe
openlegis.recipe.sagl.egg-info/requires.txt
openlegis.recipe.sagl.egg-info/top_level.txt
openlegis/recipe/__init__.py
openlegis/recipe/sagl/__init__.py
openlegis/recipe/sagl/sagl.py