Metadata-Version: 1.1
Name: openlegis.recipe.sagl
Version: 1.0.1
Summary: Recipe to create sagl as part of a buildout run
Home-page: https://github.com/openlegis-br/sagl
Author: Luciano De Fazio
Author-email: lucianodefazio@gmail.com
License: ZPL
Keywords: sagl openlegis buildout recipe
Platform: UNKNOWN
Classifier: Framework :: Buildout
Classifier: Intended Audience :: Developers
Classifier: Topic :: Software Development :: Build Tools
Classifier: Topic :: Software Development :: Libraries :: Python Modules
Classifier: License :: OSI Approved :: Zope Public License
